text_selection_component/__init__.py
text_selection_component/frontend/index.html
text_selection_component/frontend/main.js
text_selection_component/frontend/streamlit-component-lib.js
text_selection_component/frontend/style.css
text_selection_component-0.1.0.dist-info/LICENSE
text_selection_component-0.1.0.dist-info/METADATA
text_selection_component-0.1.0.dist-info/WHEEL
text_selection_component-0.1.0.dist-info/top_level.txt
text_selection_component-0.1.0.dist-info/RECORD
