Metadata-Version: 2.1
Name: text-selection-component
Version: 0.1.0
Summary: Streamlit component to get slected text in paragraph so, you process selected text
Author: Muhammad Kamran
Author-email: mkrnaqeebi@gmail.com
Requires-Python: >=3.7
License-File: LICENSE
Requires-Dist: streamlit (>=1.2)
Requires-Dist: jinja2
